simple_flask_restful/__init__.py
simple_flask_restful/decorator_method.py
simple_flask_restful/reqparse.py
simple_flask_restful/restful_exceptions.py
simple_flask_restful/simple_restful.py
simple_flask_restful-0.3.0.dist-info/LICENSE
simple_flask_restful-0.3.0.dist-info/METADATA
simple_flask_restful-0.3.0.dist-info/WHEEL
simple_flask_restful-0.3.0.dist-info/top_level.txt
simple_flask_restful-0.3.0.dist-info/RECORD
