Metadata-Version: 2.1
Name: simple-flask-restful
Version: 0.3.0
Summary: wrap up flask for restful interface
Home-page: https://github.com/AutomationLover/simple_flask_restful
Author: William Wang
Author-email: williamwangatsydney@gmail.com
License: UNKNOWN
Platform: UNKNOWN
Classifier: Programming Language :: Python :: 3
Classifier: License :: OSI Approved :: MIT License
Classifier: Operating System :: OS Independent
Requires-Python: >=3.7
License-File: LICENSE
Requires-Dist: Flask (>=2.0.1)
Requires-Dist: pytest (>=6.2.4)
